lonny_common_sql/__init__.py
lonny_common_sql/build.py
lonny_common_sql/config.py
lonny_common_sql-0.1.1.dist-info/LICENSE
lonny_common_sql-0.1.1.dist-info/WHEEL
lonny_common_sql-0.1.1.dist-info/METADATA
lonny_common_sql-0.1.1.dist-info/RECORD
