Metadata-Version: 2.1
Name: lonny-common-sql
Version: 0.1.1
Summary: A library for building inline SQL queries safely using python callables.
Home-page: https://lonny.io
Author: tlonny
Author-email: t@lonny.io
Requires-Python: >=3.8,<4.0
Classifier: Programming Language :: Python :: 3
Classifier: Programming Language :: Python :: 3.8
Project-URL: Repository, https://gitlab.com/lonny-common/sql
